birdears/__init__.py
birdears/__main__.py
birdears/exception.py
birdears/interval.py
birdears/logger.py
birdears/note_and_pitch.py
birdears/prequestion.py
birdears/questionbase.py
birdears/resolution.py
birdears/scale.py
birdears/sequence.py
birdears/utils.py
birdears/interfaces/__init__.py
birdears/interfaces/commandline.py
birdears/interfaces/urwid.py
birdears/questions/__init__.py
birdears/questions/harmonicinterval.py
birdears/questions/instrumentaldictation.py
birdears/questions/melodicdictation.py
birdears/questions/melodicinterval.py
birdears/questions/notename.py
birdears-0.3.14.dist-info/LICENSE.txt
birdears-0.3.14.dist-info/METADATA
birdears-0.3.14.dist-info/WHEEL
birdears-0.3.14.dist-info/entry_points.txt
birdears-0.3.14.dist-info/top_level.txt
birdears-0.3.14.dist-info/RECORD
