Metadata-Version: 2.1
Name: birdears
Version: 0.3.14
Summary: Functional Ear Training for Musicians
Home-page: https://github.com/iacchus/birdears/
Author: Iacchus Mercurius
Author-email: kassivs+git@gmail.com
License: AGPLv3
Project-URL: Documentation, https://birdears.readthedocs.io/
Project-URL: Source, https://github.com/iacchus/birdears/
Project-URL: Tracker, https://github.com/iacchus/birdears/issues
Platform: any
Classifier: Development Status :: 5 - Production/Stable
Classifier: Intended Audience :: Developers
Classifier: Intended Audience :: Education
Classifier: License :: OSI Approved :: GNU Affero General Public License v3
Classifier: Programming Language :: Python
Classifier: Programming Language :: Python :: 3.6
Classifier: Programming Language :: Python :: 3.7
Classifier: Programming Language :: Python :: 3.8
Classifier: Programming Language :: Python :: 3.9
Requires-Python: >=3.6
License-File: LICENSE.txt
Requires-Dist: click (>=8.0.3)
Requires-Dist: toml (>=0.10.2)
Requires-Dist: urwid (>=2.1.2)
Requires-Dist: importlib-metadata ; python_version < "3.8"
Provides-Extra: testing
Requires-Dist: setuptools ; extra == 'testing'
Requires-Dist: pytest ; extra == 'testing'
Requires-Dist: pytest-cov ; extra == 'testing'
